<?xml version="1.0" encoding="utf-8"?>
<config>
  <append xpath="/items">
    <item name="drinkJarEmpty">
      <property name="HoldType" value="3" />
      <property name="DisplayType" value="waterDysentery" />
      <property name="Meshfile" value="@:Other/Items/Food/bottled_waterPrefab.prefab" />
      <property name="DropMeshfile" value="@:Other/Items/Misc/sack_droppedPrefab.prefab" />
      <property name="Material" value="Mglass" />
      <property name="Stacknumber" value="125" />
      <!-- STK resource -->
      <!-- <property name="Weight" value="10"/> -->
      <property name="EconomicValue" value="20" />
      <property name="EconomicBundleSize" value="1" />
      <property name="SellableToTrader" value="false" />
      <property name="CraftingIngredientTime" value="10" />
      <property class="Action0">
        <property name="Class" value="CollectWater" />
        <property name="Delay" value=".35" />
        <property name="Change_item_to" value="drinkJarRiverWater" />
        <property name="Sound_start" value="bucketfill_water" />
      </property>
      <property class="Action1">
        <property name="Class" value="ExchangeItem" />
        <property name="Delay" value=".35" />
        <property name="Change_item_to" value="drinkJarRiverWater"></property>
        <property name="Do_block_action" value="deplete1" />
        <property name="Sound_start" value="bucketfill_water" />
      </property>
      <property name="Group" value="Resources" />
      <property name="CustomIcon" value="drinkJarEmpty" />
    </item>
  </append>
  <append xpath="/items/item[@name='foodHoney']/property[@class='Action0']">
    <property name="Create_item" value="drinkJarEmpty" />
  </append>
  <append xpath="/items/item[@name='drinkJarRiverWater']/property[@class='Action0']">
    <property name="Create_item" value="drinkJarEmpty" />
  </append>
  <append xpath="/items/item[@name='drinkJarBoiledWater']/property[@class='Action0']">
    <property name="Create_item" value="drinkJarEmpty" />
  </append>
  <append xpath="/items/item[@name='drinkJarPureMineralWater']/property[@class='Action0']">
    <property name="Create_item" value="drinkJarEmpty" />
  </append>
  <append xpath="/items/item[@name='drinkJarYuccaJuice']/property[@class='Action0']">
    <property name="Create_item" value="drinkJarEmpty" />
  </append>
  <append xpath="/items/item[@name='drinkJarGoldenRodTea']/property[@class='Action0']">
    <property name="Create_item" value="drinkJarEmpty" />
  </append>
  <append xpath="/items/item[@name='drinkJarRedTea']/property[@class='Action0']">
    <property name="Create_item" value="drinkJarEmpty" />
  </append>
  <append xpath="/items/item[@name='drinkYuccaJuiceSmoothie']/property[@class='Action0']">
    <property name="Create_item" value="drinkJarEmpty" />
  </append>
  <append xpath="/items/item[@name='drinkJarCoffee']/property[@class='Action0']">
    <property name="Create_item" value="drinkJarEmpty" />
  </append>
  <append xpath="/items/item[@name='drinkJarBeer']/property[@class='Action0']">
    <property name="Create_item" value="drinkJarEmpty" />
  </append>
</config>